LICENSE
MANIFEST.in
README.md
pyproject.toml
setup.cfg
setup.py
wagtail_photography/__init__.py
wagtail_photography/apps.py
wagtail_photography/blocks.py
wagtail_photography/forms.py
wagtail_photography/models.py
wagtail_photography/tests.py
wagtail_photography/views.py
wagtail_photography/wagtail_hooks.py
wagtail_photography/widgets.py
wagtail_photography.egg-info/PKG-INFO
wagtail_photography.egg-info/SOURCES.txt
wagtail_photography.egg-info/dependency_links.txt
wagtail_photography.egg-info/requires.txt
wagtail_photography.egg-info/top_level.txt
wagtail_photography/migrations/0001_initial.py
wagtail_photography/migrations/0002_remove_albumimage_height_remove_albumimage_width_and_more.py
wagtail_photography/migrations/__init__.py
wagtail_photography/static/app.js
wagtail_photography/static/photo_gallery.css
wagtail_photography/static/photo_gallery_admin.css
wagtail_photography/static/photo_gallery_admin.js
wagtail_photography/templates/includes/photo_swipe.html
wagtail_photography/templates/wagtail_photography/album_detail.html
wagtail_photography/templates/wagtail_photography/extra_css.html
wagtail_photography/templates/wagtail_photography/extra_js.html
wagtail_photography/templates/wagtail_photography/blocks/photo_gallery.html