Metadata-Version: 2.1
Name: wagtail-photography
Version: 1.0.1
Summary: A Wagtail app to display photographs
Home-page: https://github.com/TechnoConserve/wagtail-photography
Author: Avery Uslaner
Author-email: uslaner.avery@gmail.com
License: Apache License 2.0
Classifier: Environment :: Web Environment
Classifier: Framework :: Wagtail
Classifier: Framework :: Wagtail :: 4
Classifier: Intended Audience :: Developers
Classifier: License :: OSI Approved :: Apache Software License
Classifier: Operating System :: OS Independent
Classifier: Programming Language :: Python
Classifier: Programming Language :: Python :: 3
Classifier: Programming Language :: Python :: 3 :: Only
Classifier: Programming Language :: Python :: 3.8
Classifier: Programming Language :: Python :: 3.9
Classifier: Programming Language :: Python :: 3.10
Classifier: Topic :: Internet :: WWW/HTTP
Classifier: Topic :: Internet :: WWW/HTTP :: Dynamic Content
Requires-Python: >=3.8
License-File: LICENSE
